inv.cpython-311-x86_64-linux-gnu.so
testing202212-0.0.22.dist-info/RECORD
testing202212-0.0.22.dist-info/METADATA
testing202212-0.0.22.dist-info/top_level.txt
testing202212-0.0.22.dist-info/WHEEL
