Metadata-Version: 2.1
Name: testing202212
Version: 0.0.22
Summary: testing 2022_
Home-page: https://pypi.org/project/testing202212/
Author: smi
Author-email: smi@miryusupov.com
Classifier: License :: OSI Approved :: MIT License
Classifier: Programming Language :: Python :: 3
